read_daily/__init__.py
read_daily/spider/__init__.py
read_daily/spider/bilibili.py
read_daily/spider/json/bilibili-popular-response.json
read_daily-0.0.3.dist-info/METADATA
read_daily-0.0.3.dist-info/WHEEL
read_daily-0.0.3.dist-info/entry_points.txt
read_daily-0.0.3.dist-info/licenses/LICENSE
read_daily-0.0.3.dist-info/RECORD
